{
  "lastUpdate": "2026-01-30T17:13:00Z",
  "lastChecks": {
    "projects": "2026-01-30T17:13:00Z",
    "email": null,
    "calendar": null,
    "business": null,
    "memory": "2026-01-30T17:13:00Z",
    "code": "2026-01-30T17:13:00Z",
    "security": null
  },
  "currentFocus": "Market Intelligence MVP + Álv's Portfolio",
  "ongoingWork": [
    "Building automated market monitoring system",
    "Planning achievement portfolio website"
  ],
  "notes": "Álv wants data flowing ASAP for Tailor Made go-to-market. Also building portfolio for promotion."
}
